Metadata-Version: 2.1
Name: pyhepdata
Version: 0.2.1
Summary: I/O, validation, plotting, etc. of HEPData submission
Home-page: https://gitlab.com/cholmcc/hepdata
Author: Christian Holm Christensen
Author-email: cholmcc@gmail.com
License: GPLv3+
Platform: any
Classifier: Programming Language :: Python :: 3
Classifier: License :: OSI Approved :: GNU General Public License v3 or later (GPLv3+)
Classifier: Operating System :: OS Independent
Classifier: Topic :: Scientific/Engineering :: Physics
Classifier: Topic :: Scientific/Engineering :: Visualization
Classifier: Development Status :: 4 - Beta
License-File: LICENSE
Requires-Dist: hepdata-validator
Requires-Dist: jsonschema
Requires-Dist: matplotlib
Requires-Dist: pyyaml
